{
  "source_path": "/Users/nams/nas_mnt/nas2026/_AURUM_AI_PROCESSED/processed/tables/01-05_ef22343cb7.3_1-3.csv",
  "source_name": "01-05_ef22343cb7.3_1-3.csv",
  "source_type": "csv",
  "device_name": "aurum_macbook",
  "detected_at": "2026-07-08T13:42:13+09:00",
  "processed_at": "2026-07-08T13:42:20+09:00",
  "status": "success",
  "outputs": {
    "text": "/Users/nams/AI_BASE/data/processed/text/01-05_ef22343cb7.3_1-3_4491b2ef02.txt",
    "tables": [
      "/Users/nams/AI_BASE/data/processed/tables/01-05_ef22343cb7.3_1-3_4491b2ef02.csv"
    ],
    "metadata": "/Users/nams/AI_BASE/data/processed/metadata/01-05_ef22343cb7.3_1-3_4491b2ef02.metadata.json"
  },
  "error": null,
  "ai_classification": {
    "year_vendor": "unknown",
    "project_name": "unknown",
    "taxon_group": "미확정",
    "document_type": "CSV",
    "class_name": "CSV",
    "tags": [
      "#Users",
      "#nams",
      "#CSV"
    ],
    "summary": "Hermes binary not found locally.",
    "is_ambiguous": false,
    "question": ""
  },
  "ai_summary": {
    "summary": [
      "해당 문서는 '중로3진1-3'을 포함한 데이터 구조를 가진 CSV 형식의 파일입니다.",
      "총 38개의 행(row)으로 구성되어 있으며, 다수의 빈 열이 포함된 형태입니다.",
      "구체적인 수치 데이터보다는 컬럼명과 행의 개수를 파악할 수 있는 기초 문서입니다."
    ],
    "category": "기타",
    "keywords": [
      "CSV 데이터",
      "중로3진1-3",
      "데이터 구조"
    ]
  }
}