{
  "source_path": "/Users/nams/nas_mnt/nas2026/_AURUM_AI_PROCESSED/processed/tables/02.__20250206_847434e636.sheet.csv",
  "source_name": "02.__20250206_847434e636.sheet.csv",
  "source_type": "csv",
  "device_name": "aurum_macbook",
  "detected_at": "2026-07-08T13:21:00+09:00",
  "processed_at": "2026-07-08T13:21:08+09:00",
  "status": "success",
  "outputs": {
    "text": "/Users/nams/AI_BASE/data/processed/text/02.__20250206_847434e636.sheet_7e2f741e7c.txt",
    "tables": [
      "/Users/nams/AI_BASE/data/processed/tables/02.__20250206_847434e636.sheet_7e2f741e7c.csv"
    ],
    "metadata": "/Users/nams/AI_BASE/data/processed/metadata/02.__20250206_847434e636.sheet_7e2f741e7c.metadata.json"
  },
  "error": null,
  "ai_classification": {
    "year_vendor": "unknown",
    "project_name": "unknown",
    "taxon_group": "미확정",
    "document_type": "CSV",
    "class_name": "CSV",
    "tags": [
      "#Users",
      "#nams",
      "#CSV"
    ],
    "summary": "Hermes binary not found locally.",
    "is_ambiguous": false,
    "question": ""
  },
  "ai_summary": {
    "summary": [
      "제공된 데이터는 파일명과 행/열 정보만을 포함하고 있습니다.",
      "구체적인 텍스트 내용이 없어 상세 분석이 불가능합니다.",
      "데이터의 구조적 메타데이터만 확인되었습니다."
    ],
    "category": "기타",
    "keywords": [
      "CSV 데이터",
      "메타데이터",
      "분석 불가"
    ]
  }
}