{
  "source_path": "/Users/nams/nas_mnt/nas2026/_AURUM_AI_PROCESSED/processed/text/0700_15f5aa97de.txt",
  "source_name": "0700_15f5aa97de.txt",
  "source_type": "txt",
  "device_name": "aurum_macbook",
  "detected_at": "2026-07-08T11:48:08+09:00",
  "processed_at": "2026-07-08T11:48:15+09:00",
  "status": "success",
  "outputs": {
    "text": "/Users/nams/AI_BASE/data/processed/text/0700_15f5aa97de_824e299168.txt",
    "tables": [],
    "metadata": "/Users/nams/AI_BASE/data/processed/metadata/0700_15f5aa97de_824e299168.metadata.json"
  },
  "error": null,
  "ai_classification": {
    "year_vendor": "unknown",
    "project_name": "unknown",
    "taxon_group": "미확정",
    "document_type": "TXT",
    "class_name": "TXT",
    "tags": [
      "#Users",
      "#nams",
      "#TXT"
    ],
    "summary": "Hermes binary not found locally.",
    "is_ambiguous": false,
    "question": ""
  },
  "ai_summary": {
    "summary": [
      "문서 '0700 부록_수정.hwp'는 HWP 파일 형식으로 제공되었습니다.",
      "파일 크기는 55,199,232 바이트입니다.",
      "내용 추출이 지원되지 않는 파일 유형입니다."
    ],
    "category": "기타",
    "keywords": [
      "HWP 파일",
      "파일 크기",
      "내용 추출 불가"
    ]
  }
}