{
  "source_path": "/mnt/nas2026/_AURUM_AI_PROCESSED/processed/text/20250206_141937_f6c6594ef9.txt",
  "source_name": "20250206_141937_f6c6594ef9.txt",
  "source_type": "txt",
  "device_name": "overnight_batch",
  "detected_at": "2026-06-23T04:02:36+09:00",
  "processed_at": "2026-06-23T04:04:07+09:00",
  "status": "success",
  "outputs": {
    "text": "/home/caiser77/dgx_workspace/data/processed/text/20250206_141937_f6c6594ef9_64ff1466b2.txt",
    "tables": [],
    "metadata": "/home/caiser77/dgx_workspace/data/processed/metadata/20250206_141937_f6c6594ef9_64ff1466b2.metadata.json"
  },
  "error": null,
  "ai_classification": {
    "class_name": "현장조사",
    "summary": "삼성 스마트폰으로 촬영된 고화질 사진\n사진은 2025년 2월 6일 14시 19분 37초에 촬영됨\nGPS 좌표는 34.449245, 127.48469로 고흥 지역에서 촬영",
    "tags": [
      "#사진",
      "#고흥",
      "#GPS"
    ],
    "is_ambiguous": false,
    "question": ""
  },
  "ai_summary": {
    "summary": [
      "삼성 스마트폰으로 촬영된 고화질 사진",
      "사진은 2025년 2월 6일 14시 19분 37초에 촬영됨",
      "GPS 좌표는 34.449245, 127.48469로 고흥 지역에서 촬영"
    ],
    "category": "현장조사",
    "keywords": [
      "사진",
      "고흥",
      "GPS"
    ]
  }
}