{
  "source_path": "/mnt/nas2026/_AURUM_AI_PROCESSED/processed/text/4_448bda63af.txt",
  "source_name": "4_448bda63af.txt",
  "source_type": "txt",
  "device_name": "overnight_batch",
  "detected_at": "2026-06-23T21:21:13+09:00",
  "processed_at": "2026-06-23T21:22:20+09:00",
  "status": "success",
  "outputs": {
    "text": "/home/caiser77/dgx_workspace/data/processed/text/4_448bda63af_a8177703ce.txt",
    "tables": [],
    "metadata": "/home/caiser77/dgx_workspace/data/processed/metadata/4_448bda63af_a8177703ce.metadata.json"
  },
  "error": null,
  "ai_classification": {
    "year_vendor": "2026 아라기술",
    "project_name": "오천항 정비공사 사후",
    "class_name": "수달",
    "tags": [
      "#수달",
      "#오천항",
      "#정비공사"
    ],
    "summary": "2026년 3월 20일 오천항에서 촬영된 수달 사진. Panasonic DC-TZ99 카메라로 촬영.",
    "is_ambiguous": false,
    "question": ""
  },
  "ai_summary": {
    "summary": [
      "2026년 3월 20일 오전 10시 39분에 촬영된 수달 사진",
      "Panasonic DC-TZ99 카메라로 남이에서 촬영",
      "GPS 좌표: 위도 36.443042, 경도 126.515625"
    ],
    "category": "현장조사",
    "keywords": [
      "수달",
      "남이",
      "GPS"
    ]
  }
}