{
  "source_path": "/mnt/nas2026/_AURUM_AI_PROCESSED/processed/text/BM1-0712__2026.05.07_c67b90d2c3.txt",
  "source_name": "BM1-0712__2026.05.07_c67b90d2c3.txt",
  "source_type": "txt",
  "device_name": "overnight_batch",
  "detected_at": "2026-07-01T11:50:53+09:00",
  "processed_at": "2026-07-01T11:50:53+09:00",
  "status": "failed",
  "outputs": {
    "text": null,
    "tables": [],
    "metadata": null
  },
  "error": {
    "type": "FileNotFoundError",
    "message": "input file not found: /mnt/nas2026/_AURUM_AI_PROCESSED/processed/text/BM1-0712__2026.05.07_c67b90d2c3.txt",
    "return_code": 1
  }
}