{
  "source_path": "/Users/nams/nas_mnt/nas2026/_AURUM_AI_PROCESSED/processed/text/DD-000_31a5ca179b.txt",
  "source_name": "DD-000_31a5ca179b.txt",
  "source_type": "txt",
  "device_name": "aurum_macbook",
  "detected_at": "2026-07-08T13:44:07+09:00",
  "processed_at": "2026-07-08T13:44:14+09:00",
  "status": "success",
  "outputs": {
    "text": "/Users/nams/AI_BASE/data/processed/text/DD-000_31a5ca179b_2c932d59a1.txt",
    "tables": [],
    "metadata": "/Users/nams/AI_BASE/data/processed/metadata/DD-000_31a5ca179b_2c932d59a1.metadata.json"
  },
  "error": null,
  "ai_classification": {
    "year_vendor": "unknown",
    "project_name": "unknown",
    "taxon_group": "미확정",
    "document_type": "TXT",
    "class_name": "TXT",
    "tags": [
      "#Users",
      "#nams",
      "#TXT"
    ],
    "summary": "Hermes binary not found locally.",
    "is_ambiguous": false,
    "question": ""
  },
  "ai_summary": {
    "summary": [
      "해당 문서는 PDF 형식의 파일로 크기는 51,588 바이트입니다.",
      "파일 유형 문제로 인해 직접적인 내용 추출이 지원되지 않습니다.",
      "ASCII 인코딩 오류로 인해 특정 문자 처리 과정에서 문제가 발생했습니다."
    ],
    "category": "행정문서",
    "keywords": [
      "PDF",
      "파일 크기",
      "인코딩 오류"
    ]
  }
}