{
  "source_path": "/Users/nams/nas_mnt/nas2026/_AURUM_AI_PROCESSED/processed/text/R0039792_afb1c807e7.txt",
  "source_name": "R0039792_afb1c807e7.txt",
  "source_type": "txt",
  "device_name": "aurum_macbook",
  "detected_at": "2026-07-08T14:35:31+09:00",
  "processed_at": "2026-07-08T14:35:38+09:00",
  "status": "success",
  "outputs": {
    "text": "/Users/nams/AI_BASE/data/processed/text/R0039792_afb1c807e7_8ee99926b7.txt",
    "tables": [],
    "metadata": "/Users/nams/AI_BASE/data/processed/metadata/R0039792_afb1c807e7_8ee99926b7.metadata.json"
  },
  "error": null,
  "ai_classification": {
    "year_vendor": "unknown",
    "project_name": "unknown",
    "taxon_group": "미확정",
    "document_type": "TXT",
    "class_name": "TXT",
    "tags": [
      "#Users",
      "#nams",
      "#TXT"
    ],
    "summary": "Hermes binary not found locally.",
    "is_ambiguous": false,
    "question": ""
  },
  "ai_summary": {
    "summary": [
      "RICOH WG-6 카메라로 촬영된 주름다슬기 사진 데이터입니다.",
      "2026년 3월 6일 낮 12시 59분에 촬영되었습니다.",
      "군포 대야미 지역의 유과 지점 현장 조사 기록물입니다."
    ],
    "category": "현장조사",
    "keywords": [
      "주름다슬기",
      "군포대야미",
      "현장사진"
    ]
  }
}