{
  "source_path": "/Users/nams/nas_mnt/nas2026/_AURUM_AI_PROCESSED/processed/text/RCNX0107-_94ec98a690.txt",
  "source_name": "RCNX0107-_94ec98a690.txt",
  "source_type": "txt",
  "device_name": "aurum_macbook",
  "detected_at": "2026-07-08T09:03:29+09:00",
  "processed_at": "2026-07-08T09:03:37+09:00",
  "status": "success",
  "outputs": {
    "text": "/Users/nams/AI_BASE/data/processed/text/RCNX0107-_94ec98a690_831f1152df.txt",
    "tables": [],
    "metadata": "/Users/nams/AI_BASE/data/processed/metadata/RCNX0107-_94ec98a690_831f1152df.metadata.json"
  },
  "error": null,
  "ai_classification": {
    "year_vendor": "unknown",
    "project_name": "unknown",
    "taxon_group": "미확정",
    "document_type": "TXT",
    "class_name": "TXT",
    "tags": [
      "#Users",
      "#nams",
      "#TXT"
    ],
    "summary": "Hermes binary not found locally.",
    "is_ambiguous": false,
    "question": ""
  },
  "ai_summary": {
    "summary": [
      "울산 온산국가산업단지 인근 무인 카메라로 촬영된 고라니 사진 데이터입니다.",
      "2025년 8월 2일 RECONYX HYPERFIRE 2 모델을 통해 촬영되었습니다.",
      "1차 조사(25.07.28-30) 과정 중 상단 지점에서 수집된 생태 기록입니다."
    ],
    "category": "현장조사",
    "keywords": [
      "고라니",
      "무인카메라",
      "울산 온산국가산업단지"
    ]
  }
}